dnnlib/__init__.py
dnnlib/util.py
jam_data/__init__.py
jam_data/cli/__init__.py
jam_data/cli/dataset_tool.py
jam_data/mock_dataset.py
jam_data/tero_dataset.py
jam_data/toy_sample.py
jam_data/utils/__init__.py
jam_data/utils/url_helper.py
jam_data-0.0.6.dist-info/METADATA
jam_data-0.0.6.dist-info/WHEEL
jam_data-0.0.6.dist-info/entry_points.txt
jam_data-0.0.6.dist-info/RECORD
