Metadata-Version: 2.1
Name: jam_data
Version: 0.0.6
Summary: some data utils
Author: qsh.27
Requires-Python: >=3.8.1,<3.12
Classifier: Programming Language :: Python :: 3
Classifier: Programming Language :: Python :: 3.9
Classifier: Programming Language :: Python :: 3.10
Classifier: Programming Language :: Python :: 3.11
Requires-Dist: einops (>=0.7.0,<0.8.0)
Requires-Dist: loguru (>=0.7.2,<0.8.0)
Requires-Dist: setuptools (>=59.6.0,<60.0.0)
